{"updated": "22:10", "trains": [{"aimed": "23:30", "expected": "23:32", "destination": "London Cannon Street", "platform": "1", "operator": "Southeastern", "callingPoints": ["London Bridge", "London Cannon Street"], "cancelled": false}, {"aimed": "23:44", "expected": "On time", "destination": "Dartford", "platform": "1", "operator": "Southeastern", "callingPoints": ["London Bridge", "London Cannon Street"], "cancelled": false}, {"aimed": "00:14", "expected": "On time", "destination": "Dartford", "platform": "", "operator": "Southeastern", "callingPoints": ["London Bridge"], "cancelled": false}, {"aimed": "00:24", "expected": "On time", "destination": "London Bridge", "platform": "", "operator": "Southeastern", "callingPoints": ["Greenwich", "Maze Hill", "Westcombe Park", "Charlton", "Woolwich Dockyard", "Woolwich Arsenal", "Plumstead", "Abbey Wood", "Belvedere", "Erith", "Slade Green", "Dartford"], "cancelled": false}, {"aimed": "00:54", "expected": "On time", "destination": "London Bridge", "platform": "", "operator": "Southeastern", "callingPoints": ["Greenwich", "Maze Hill", "Westcombe Park", "Charlton", "Woolwich Dockyard", "Woolwich Arsenal", "Plumstead", "Abbey Wood", "Belvedere", "Erith", "Slade Green", "Dartford"], "cancelled": false}]}