{"updated": "05:50", "trains": [{"aimed": "05:49", "expected": "On time", "destination": "Gillingham (Kent)", "platform": "1", "operator": "Thameslink", "callingPoints": ["London Bridge", "London Blackfriars", "Farringdon", "London St Pancras (Intl)", "Kentish Town", "West Hampstead Thameslink", "Cricklewood", "Brent Cross West", "Hendon", "Mill Hill Broadway", "Elstree & Borehamwood", "Radlett", "St Albans"], "cancelled": false}, {"aimed": "06:02", "expected": "On time", "destination": "Slade Green", "platform": "1", "operator": "Southeastern", "callingPoints": ["London Bridge", "London Cannon Street"], "cancelled": false}, {"aimed": "06:19", "expected": "On time", "destination": "Gillingham (Kent)", "platform": "1", "operator": "Thameslink", "callingPoints": ["London Bridge", "London Blackfriars", "Farringdon", "London St Pancras (Intl)", "West Hampstead Thameslink", "Brent Cross West", "Mill Hill Broadway", "Elstree & Borehamwood", "Radlett", "St Albans", "Harpenden", "Luton Airport Parkway", "Luton"], "cancelled": false}, {"aimed": "06:32", "expected": "On time", "destination": "Slade Green", "platform": "1", "operator": "Southeastern", "callingPoints": ["London Bridge", "London Cannon Street"], "cancelled": false}, {"aimed": "06:49", "expected": "On time", "destination": "Rainham (Kent)", "platform": "1", "operator": "Thameslink", "callingPoints": ["London Bridge", "London Blackfriars", "Farringdon", "London St Pancras (Intl)", "West Hampstead Thameslink", "Brent Cross West", "Mill Hill Broadway", "Elstree & Borehamwood", "Radlett", "St Albans", "Harpenden", "Luton Airport Parkway", "Luton"], "cancelled": false}]}