{"updated": "15:08", "trains": [{"aimed": "16:19", "expected": "On time", "destination": "Rainham (Kent)", "platform": "1", "operator": "Thameslink", "callingPoints": ["London Bridge", "London Blackfriars", "Farringdon", "London St Pancras (Intl)", "Kentish Town", "West Hampstead Thameslink", "Cricklewood", "Brent Cross West", "Hendon", "Mill Hill Broadway", "Elstree & Borehamwood", "Radlett", "St Albans", "Harpenden", "Luton Airport Parkway", "Luton"], "cancelled": false}, {"aimed": "16:32", "expected": "On time", "destination": "Dartford", "platform": "1", "operator": "Southeastern", "callingPoints": ["London Bridge"], "cancelled": false}, {"aimed": "16:49", "expected": "On time", "destination": "Rainham (Kent)", "platform": "1", "operator": "Thameslink", "callingPoints": ["London Bridge", "London Blackfriars", "Farringdon", "London St Pancras (Intl)", "Kentish Town", "West Hampstead Thameslink", "Cricklewood", "Brent Cross West", "Hendon", "Mill Hill Broadway", "Elstree & Borehamwood", "Radlett", "St Albans", "Harpenden", "Luton Airport Parkway", "Luton"], "cancelled": false}, {"aimed": "17:02", "expected": "On time", "destination": "Dartford", "platform": "1", "operator": "Southeastern", "callingPoints": ["London Bridge"], "cancelled": false}, {"aimed": "17:19", "expected": "On time", "destination": "Rainham (Kent)", "platform": "", "operator": "Thameslink", "callingPoints": ["London Bridge", "London Blackfriars", "Farringdon", "London St Pancras (Intl)", "Kentish Town", "West Hampstead Thameslink", "Cricklewood", "Brent Cross West", "Hendon", "Mill Hill Broadway", "Elstree & Borehamwood", "Radlett", "St Albans", "Harpenden", "Luton Airport Parkway", "Luton"], "cancelled": false}]}