{"updated": "17:43", "trains": [{"aimed": "16:59", "expected": "17:41", "destination": "Slade Green", "platform": "1", "operator": "Southeastern", "callingPoints": ["London Bridge", "London Cannon Street"], "cancelled": false}, {"aimed": "17:09", "expected": "17:44", "destination": "London Cannon Street", "platform": "1", "operator": "Southeastern", "callingPoints": ["London Bridge", "London Cannon Street"], "cancelled": false}, {"aimed": "17:39", "expected": "17:50", "destination": "London Cannon Street", "platform": "1", "operator": "Southeastern", "callingPoints": ["London Bridge", "London Cannon Street"], "cancelled": false}, {"aimed": "17:49", "expected": "17:53", "destination": "Rainham (Kent)", "platform": "1", "operator": "Thameslink", "callingPoints": ["London Bridge", "London Blackfriars", "City Thameslink", "Farringdon", "London St Pancras (Intl)", "West Hampstead Thameslink", "Brent Cross West", "Mill Hill Broadway", "Elstree & Borehamwood", "Radlett", "St Albans", "Harpenden", "Luton Airport Parkway", "Luton"], "cancelled": false}, {"aimed": "17:59", "expected": "18:09", "destination": "London Cannon Street", "platform": "1", "operator": "Southeastern", "callingPoints": ["London Bridge", "London Cannon Street"], "cancelled": false}, {"aimed": "18:03", "expected": "Cancelled", "destination": "London Cannon Street", "platform": "", "operator": "Southeastern", "callingPoints": ["Greenwich", "Maze Hill", "Westcombe Park", "Charlton", "Woolwich Dockyard", "Woolwich Arsenal", "Plumstead", "Abbey Wood", "Belvedere", "Erith", "Slade Green", "Barnehurst", "Bexleyheath", "Welling", "Falconwood", "Eltham", "Kidbrooke", "Blackheath", "Lewisham", "St Johns", "New Cross", "London Bridge", "London Cannon Street"], "cancelled": true}, {"aimed": "18:09", "expected": "Delayed", "destination": "London Cannon Street", "platform": "1", "operator": "Southeastern", "callingPoints": ["London Bridge", "London Cannon Street"], "cancelled": false}]}